CompareStrings.py
helpers/helpers.py
compare_strings-0.0.3.dist-info/LICENSE.txt
compare_strings-0.0.3.dist-info/METADATA
compare_strings-0.0.3.dist-info/WHEEL
compare_strings-0.0.3.dist-info/top_level.txt
compare_strings-0.0.3.dist-info/RECORD
