Metadata-Version: 2.1
Name: compare-strings
Version: 0.0.3
Summary: A library for measuring similarity between strings
Home-page: UNKNOWN
License: UNKNOWN
Platform: UNKNOWN
Classifier: Programming Language :: Python :: 3
Classifier: Programming Language :: Python :: 3.6
Classifier: Programming Language :: Python :: 3.7
Classifier: License :: OSI Approved :: MIT License
Classifier: Operating System :: OS Independent
Classifier: Intended Audience :: Financial and Insurance Industry
Requires-Dist: pandas (>=1.2.4)
Requires-Dist: numpy (>=1.19.5)
Requires-Dist: python-Levenshtein (>=0.12.2)
Provides-Extra: dev
Requires-Dist: pytest (>=3.7) ; extra == 'dev'
